<?xml version="1.0" encoding="utf-8"?>
<DialogueTree>
  <Nodes>
    <DialogueNode>
      <id>54</id>
      <readyToInit>true</readyToInit>
      <rect>
        <x>249</x>
        <y>38</y>
        <position>
          <x>249</x>
          <y>38</y>
        </position>
        <center>
          <x>349</x>
          <y>129</y>
        </center>
        <min>
          <x>249</x>
          <y>38</y>
        </min>
        <max>
          <x>449</x>
          <y>220</y>
        </max>
        <width>200</width>
        <height>182</height>
        <size>
          <x>200</x>
          <y>182</y>
        </size>
        <xMin>249</xMin>
        <yMin>38</yMin>
        <xMax>449</xMax>
        <yMax>220</yMax>
      </rect>
      <defaultRect>
        <x>284</x>
        <y>559</y>
        <position>
          <x>284</x>
          <y>559</y>
        </position>
        <center>
          <x>384</x>
          <y>629</y>
        </center>
        <min>
          <x>284</x>
          <y>559</y>
        </min>
        <max>
          <x>484</x>
          <y>699</y>
        </max>
        <width>200</width>
        <height>140</height>
        <size>
          <x>200</x>
          <y>140</y>
        </size>
        <xMin>284</xMin>
        <yMin>559</yMin>
        <xMax>484</xMax>
        <yMax>699</yMax>
      </defaultRect>
      <dialogue>Hey Dave, what were you about to say earlier? You seemed to have something on your mind. </dialogue>
      <character>player</character>
      <expression>sad</expression>
      <advancedOptions>false</advancedOptions>
      <characterAffected>player</characterAffected>
      <forceLeft>false</forceLeft>
      <longOption>false</longOption>
      <positive>false</positive>
      <negative>false</negative>
      <infoGathered>-1</infoGathered>
      <fired>false</fired>
      <restrictions>false</restrictions>
      <characterRestriction>player</characterRestriction>
      <positiveRestriction>99</positiveRestriction>
      <negativeRestriction>1</negativeRestriction>
      <infoRestriction>-1</infoRestriction>
      <isDragged>false</isDragged>
      <isSelected>false</isSelected>
      <inPoint type="In">
        <id>54</id>
        <readyToInit>true</readyToInit>
        <rect>
          <x>339</x>
          <y>33</y>
          <position>
            <x>339</x>
            <y>33</y>
          </position>
          <center>
            <x>349</x>
            <y>38</y>
          </center>
          <min>
            <x>339</x>
            <y>33</y>
          </min>
          <max>
            <x>359</x>
            <y>43</y>
          </max>
          <width>20</width>
          <height>10</height>
          <size>
            <x>20</x>
            <y>10</y>
          </size>
          <xMin>339</xMin>
          <yMin>33</yMin>
          <xMax>359</xMax>
          <yMax>43</yMax>
        </rect>
        <nodeRect>
          <x>249</x>
          <y>38</y>
          <position>
            <x>249</x>
            <y>38</y>
          </position>
          <center>
            <x>349</x>
            <y>129</y>
          </center>
          <min>
            <x>249</x>
            <y>38</y>
          </min>
          <max>
            <x>449</x>
            <y>220</y>
          </max>
          <width>200</width>
          <height>182</height>
          <size>
            <x>200</x>
            <y>182</y>
          </size>
          <xMin>249</xMin>
          <yMin>38</yMin>
          <xMax>449</xMax>
          <yMax>220</yMax>
        </nodeRect>
      </inPoint>
      <outPoint type="Out">
        <id>54</id>
        <readyToInit>true</readyToInit>
        <rect>
          <x>339</x>
          <y>213</y>
          <position>
            <x>339</x>
            <y>213</y>
          </position>
          <center>
            <x>349</x>
            <y>218</y>
          </center>
          <min>
            <x>339</x>
            <y>213</y>
          </min>
          <max>
            <x>359</x>
            <y>223</y>
          </max>
          <width>20</width>
          <height>10</height>
          <size>
            <x>20</x>
            <y>10</y>
          </size>
          <xMin>339</xMin>
          <yMin>213</yMin>
          <xMax>359</xMax>
          <yMax>223</yMax>
        </rect>
        <nodeRect>
          <x>249</x>
          <y>38</y>
          <position>
            <x>249</x>
            <y>38</y>
          </position>
          <center>
            <x>349</x>
            <y>129</y>
          </center>
          <min>
            <x>249</x>
            <y>38</y>
          </min>
          <max>
            <x>449</x>
            <y>220</y>
          </max>
          <width>200</width>
          <height>182</height>
          <size>
            <x>200</x>
            <y>182</y>
          </size>
          <xMin>249</xMin>
          <yMin>38</yMin>
          <xMax>449</xMax>
          <yMax>220</yMax>
        </nodeRect>
      </outPoint>
    </DialogueNode>
    <DialogueNode>
      <id>56</id>
      <readyToInit>true</readyToInit>
      <rect>
        <x>249</x>
        <y>414</y>
        <position>
          <x>249</x>
          <y>414</y>
        </position>
        <center>
          <x>349</x>
          <y>498.5</y>
        </center>
        <min>
          <x>249</x>
          <y>414</y>
        </min>
        <max>
          <x>449</x>
          <y>583</y>
        </max>
        <width>200</width>
        <height>169</height>
        <size>
          <x>200</x>
          <y>169</y>
        </size>
        <xMin>249</xMin>
        <yMin>414</yMin>
        <xMax>449</xMax>
        <yMax>583</yMax>
      </rect>
      <defaultRect>
        <x>239</x>
        <y>586</y>
        <position>
          <x>239</x>
          <y>586</y>
        </position>
        <center>
          <x>339</x>
          <y>656</y>
        </center>
        <min>
          <x>239</x>
          <y>586</y>
        </min>
        <max>
          <x>439</x>
          <y>726</y>
        </max>
        <width>200</width>
        <height>140</height>
        <size>
          <x>200</x>
          <y>140</y>
        </size>
        <xMin>239</xMin>
        <yMin>586</yMin>
        <xMax>439</xMax>
        <yMax>726</yMax>
      </defaultRect>
      <dialogue>Well . . . Okay. I trust you're here to help, Alex.</dialogue>
      <character>dave</character>
      <expression>neutral</expression>
      <advancedOptions>false</advancedOptions>
      <characterAffected>player</characterAffected>
      <forceLeft>false</forceLeft>
      <longOption>false</longOption>
      <positive>false</positive>
      <negative>false</negative>
      <infoGathered>-1</infoGathered>
      <fired>false</fired>
      <restrictions>false</restrictions>
      <characterRestriction>player</characterRestriction>
      <positiveRestriction>99</positiveRestriction>
      <negativeRestriction>-99</negativeRestriction>
      <infoRestriction>-1</infoRestriction>
      <isDragged>false</isDragged>
      <isSelected>false</isSelected>
      <inPoint type="In">
        <id>56</id>
        <readyToInit>true</readyToInit>
        <rect>
          <x>339</x>
          <y>409</y>
          <position>
            <x>339</x>
            <y>409</y>
          </position>
          <center>
            <x>349</x>
            <y>414</y>
          </center>
          <min>
            <x>339</x>
            <y>409</y>
          </min>
          <max>
            <x>359</x>
            <y>419</y>
          </max>
          <width>20</width>
          <height>10</height>
          <size>
            <x>20</x>
            <y>10</y>
          </size>
          <xMin>339</xMin>
          <yMin>409</yMin>
          <xMax>359</xMax>
          <yMax>419</yMax>
        </rect>
        <nodeRect>
          <x>249</x>
          <y>414</y>
          <position>
            <x>249</x>
            <y>414</y>
          </position>
          <center>
            <x>349</x>
            <y>498.5</y>
          </center>
          <min>
            <x>249</x>
            <y>414</y>
          </min>
          <max>
            <x>449</x>
            <y>583</y>
          </max>
          <width>200</width>
          <height>169</height>
          <size>
            <x>200</x>
            <y>169</y>
          </size>
          <xMin>249</xMin>
          <yMin>414</yMin>
          <xMax>449</xMax>
          <yMax>583</yMax>
        </nodeRect>
      </inPoint>
      <outPoint type="Out">
        <id>56</id>
        <readyToInit>true</readyToInit>
        <rect>
          <x>339</x>
          <y>576</y>
          <position>
            <x>339</x>
            <y>576</y>
          </position>
          <center>
            <x>349</x>
            <y>581</y>
          </center>
          <min>
            <x>339</x>
            <y>576</y>
          </min>
          <max>
            <x>359</x>
            <y>586</y>
          </max>
          <width>20</width>
          <height>10</height>
          <size>
            <x>20</x>
            <y>10</y>
          </size>
          <xMin>339</xMin>
          <yMin>576</yMin>
          <xMax>359</xMax>
          <yMax>586</yMax>
        </rect>
        <nodeRect>
          <x>249</x>
          <y>414</y>
          <position>
            <x>249</x>
            <y>414</y>
          </position>
          <center>
            <x>349</x>
            <y>498.5</y>
          </center>
          <min>
            <x>249</x>
            <y>414</y>
          </min>
          <max>
            <x>449</x>
            <y>583</y>
          </max>
          <width>200</width>
          <height>169</height>
          <size>
            <x>200</x>
            <y>169</y>
          </size>
          <xMin>249</xMin>
          <yMin>414</yMin>
          <xMax>449</xMax>
          <yMax>583</yMax>
        </nodeRect>
      </outPoint>
    </DialogueNode>
    <DialogueNode>
      <id>57</id>
      <readyToInit>true</readyToInit>
      <rect>
        <x>250</x>
        <y>634</y>
        <position>
          <x>250</x>
          <y>634</y>
        </position>
        <center>
          <x>350</x>
          <y>738</y>
        </center>
        <min>
          <x>250</x>
          <y>634</y>
        </min>
        <max>
          <x>450</x>
          <y>842</y>
        </max>
        <width>200</width>
        <height>208</height>
        <size>
          <x>200</x>
          <y>208</y>
        </size>
        <xMin>250</xMin>
        <yMin>634</yMin>
        <xMax>450</xMax>
        <yMax>842</yMax>
      </rect>
      <defaultRect>
        <x>314</x>
        <y>744</y>
        <position>
          <x>314</x>
          <y>744</y>
        </position>
        <center>
          <x>414</x>
          <y>814</y>
        </center>
        <min>
          <x>314</x>
          <y>744</y>
        </min>
        <max>
          <x>514</x>
          <y>884</y>
        </max>
        <width>200</width>
        <height>140</height>
        <size>
          <x>200</x>
          <y>140</y>
        </size>
        <xMin>314</xMin>
        <yMin>744</yMin>
        <xMax>514</xMax>
        <yMax>884</yMax>
      </defaultRect>
      <dialogue>The other day Stan totally blew up at Sharon. He told her that she needs to stop letting her "hormones interfere with her work."</dialogue>
      <character>dave</character>
      <expression>angry</expression>
      <advancedOptions>false</advancedOptions>
      <characterAffected>player</characterAffected>
      <forceLeft>false</forceLeft>
      <longOption>false</longOption>
      <positive>false</positive>
      <negative>false</negative>
      <infoGathered>-1</infoGathered>
      <fired>false</fired>
      <restrictions>false</restrictions>
      <characterRestriction>player</characterRestriction>
      <positiveRestriction>99</positiveRestriction>
      <negativeRestriction>-99</negativeRestriction>
      <infoRestriction>-1</infoRestriction>
      <isDragged>false</isDragged>
      <isSelected>false</isSelected>
      <inPoint type="In">
        <id>57</id>
        <readyToInit>true</readyToInit>
        <rect>
          <x>340</x>
          <y>629</y>
          <position>
            <x>340</x>
            <y>629</y>
          </position>
          <center>
            <x>350</x>
            <y>634</y>
          </center>
          <min>
            <x>340</x>
            <y>629</y>
          </min>
          <max>
            <x>360</x>
            <y>639</y>
          </max>
          <width>20</width>
          <height>10</height>
          <size>
            <x>20</x>
            <y>10</y>
          </size>
          <xMin>340</xMin>
          <yMin>629</yMin>
          <xMax>360</xMax>
          <yMax>639</yMax>
        </rect>
        <nodeRect>
          <x>250</x>
          <y>634</y>
          <position>
            <x>250</x>
            <y>634</y>
          </position>
          <center>
            <x>350</x>
            <y>738</y>
          </center>
          <min>
            <x>250</x>
            <y>634</y>
          </min>
          <max>
            <x>450</x>
            <y>842</y>
          </max>
          <width>200</width>
          <height>208</height>
          <size>
            <x>200</x>
            <y>208</y>
          </size>
          <xMin>250</xMin>
          <yMin>634</yMin>
          <xMax>450</xMax>
          <yMax>842</yMax>
        </nodeRect>
      </inPoint>
      <outPoint type="Out">
        <id>57</id>
        <readyToInit>true</readyToInit>
        <rect>
          <x>340</x>
          <y>835</y>
          <position>
            <x>340</x>
            <y>835</y>
          </position>
          <center>
            <x>350</x>
            <y>840</y>
          </center>
          <min>
            <x>340</x>
            <y>835</y>
          </min>
          <max>
            <x>360</x>
            <y>845</y>
          </max>
          <width>20</width>
          <height>10</height>
          <size>
            <x>20</x>
            <y>10</y>
          </size>
          <xMin>340</xMin>
          <yMin>835</yMin>
          <xMax>360</xMax>
          <yMax>845</yMax>
        </rect>
        <nodeRect>
          <x>250</x>
          <y>634</y>
          <position>
            <x>250</x>
            <y>634</y>
          </position>
          <center>
            <x>350</x>
            <y>738</y>
          </center>
          <min>
            <x>250</x>
            <y>634</y>
          </min>
          <max>
            <x>450</x>
            <y>842</y>
          </max>
          <width>200</width>
          <height>208</height>
          <size>
            <x>200</x>
            <y>208</y>
          </size>
          <xMin>250</xMin>
          <yMin>634</yMin>
          <xMax>450</xMax>
          <yMax>842</yMax>
        </nodeRect>
      </outPoint>
    </DialogueNode>
    <DialogueNode>
      <id>58</id>
      <readyToInit>true</readyToInit>
      <rect>
        <x>252</x>
        <y>901</y>
        <position>
          <x>252</x>
          <y>901</y>
        </position>
        <center>
          <x>352</x>
          <y>985.5</y>
        </center>
        <min>
          <x>252</x>
          <y>901</y>
        </min>
        <max>
          <x>452</x>
          <y>1070</y>
        </max>
        <width>200</width>
        <height>169</height>
        <size>
          <x>200</x>
          <y>169</y>
        </size>
        <xMin>252</xMin>
        <yMin>901</yMin>
        <xMax>452</xMax>
        <yMax>1070</yMax>
      </rect>
      <defaultRect>
        <x>329</x>
        <y>696</y>
        <position>
          <x>329</x>
          <y>696</y>
        </position>
        <center>
          <x>429</x>
          <y>766</y>
        </center>
        <min>
          <x>329</x>
          <y>696</y>
        </min>
        <max>
          <x>529</x>
          <y>836</y>
        </max>
        <width>200</width>
        <height>140</height>
        <size>
          <x>200</x>
          <y>140</y>
        </size>
        <xMin>329</xMin>
        <yMin>696</yMin>
        <xMax>529</xMax>
        <yMax>836</yMax>
      </defaultRect>
      <dialogue> She was so embarrassed... She left early.</dialogue>
      <character>dave</character>
      <expression>sad</expression>
      <advancedOptions>false</advancedOptions>
      <characterAffected>player</characterAffected>
      <forceLeft>false</forceLeft>
      <longOption>false</longOption>
      <positive>false</positive>
      <negative>false</negative>
      <infoGathered>-1</infoGathered>
      <fired>false</fired>
      <restrictions>false</restrictions>
      <characterRestriction>player</characterRestriction>
      <positiveRestriction>99</positiveRestriction>
      <negativeRestriction>-99</negativeRestriction>
      <infoRestriction>-1</infoRestriction>
      <isDragged>false</isDragged>
      <isSelected>false</isSelected>
      <inPoint type="In">
        <id>58</id>
        <readyToInit>true</readyToInit>
        <rect>
          <x>342</x>
          <y>896</y>
          <position>
            <x>342</x>
            <y>896</y>
          </position>
          <center>
            <x>352</x>
            <y>901</y>
          </center>
          <min>
            <x>342</x>
            <y>896</y>
          </min>
          <max>
            <x>362</x>
            <y>906</y>
          </max>
          <width>20</width>
          <height>10</height>
          <size>
            <x>20</x>
            <y>10</y>
          </size>
          <xMin>342</xMin>
          <yMin>896</yMin>
          <xMax>362</xMax>
          <yMax>906</yMax>
        </rect>
        <nodeRect>
          <x>252</x>
          <y>901</y>
          <position>
            <x>252</x>
            <y>901</y>
          </position>
          <center>
            <x>352</x>
            <y>985.5</y>
          </center>
          <min>
            <x>252</x>
            <y>901</y>
          </min>
          <max>
            <x>452</x>
            <y>1070</y>
          </max>
          <width>200</width>
          <height>169</height>
          <size>
            <x>200</x>
            <y>169</y>
          </size>
          <xMin>252</xMin>
          <yMin>901</yMin>
          <xMax>452</xMax>
          <yMax>1070</yMax>
        </nodeRect>
      </inPoint>
      <outPoint type="Out">
        <id>58</id>
        <readyToInit>true</readyToInit>
        <rect>
          <x>342</x>
          <y>1063</y>
          <position>
            <x>342</x>
            <y>1063</y>
          </position>
          <center>
            <x>352</x>
            <y>1068</y>
          </center>
          <min>
            <x>342</x>
            <y>1063</y>
          </min>
          <max>
            <x>362</x>
            <y>1073</y>
          </max>
          <width>20</width>
          <height>10</height>
          <size>
            <x>20</x>
            <y>10</y>
          </size>
          <xMin>342</xMin>
          <yMin>1063</yMin>
          <xMax>362</xMax>
          <yMax>1073</yMax>
        </rect>
        <nodeRect>
          <x>252</x>
          <y>901</y>
          <position>
            <x>252</x>
            <y>901</y>
          </position>
          <center>
            <x>352</x>
            <y>985.5</y>
          </center>
          <min>
            <x>252</x>
            <y>901</y>
          </min>
          <max>
            <x>452</x>
            <y>1070</y>
          </max>
          <width>200</width>
          <height>169</height>
          <size>
            <x>200</x>
            <y>169</y>
          </size>
          <xMin>252</xMin>
          <yMin>901</yMin>
          <xMax>452</xMax>
          <yMax>1070</yMax>
        </nodeRect>
      </outPoint>
    </DialogueNode>
    <DialogueNode>
      <id>59</id>
      <readyToInit>true</readyToInit>
      <rect>
        <x>253</x>
        <y>1137</y>
        <position>
          <x>253</x>
          <y>1137</y>
        </position>
        <center>
          <x>353</x>
          <y>1241</y>
        </center>
        <min>
          <x>253</x>
          <y>1137</y>
        </min>
        <max>
          <x>453</x>
          <y>1345</y>
        </max>
        <width>200</width>
        <height>208</height>
        <size>
          <x>200</x>
          <y>208</y>
        </size>
        <xMin>253</xMin>
        <yMin>1137</yMin>
        <xMax>453</xMax>
        <yMax>1345</yMax>
      </rect>
      <defaultRect>
        <x>405</x>
        <y>499</y>
        <position>
          <x>405</x>
          <y>499</y>
        </position>
        <center>
          <x>505</x>
          <y>569</y>
        </center>
        <min>
          <x>405</x>
          <y>499</y>
        </min>
        <max>
          <x>605</x>
          <y>639</y>
        </max>
        <width>200</width>
        <height>140</height>
        <size>
          <x>200</x>
          <y>140</y>
        </size>
        <xMin>405</xMin>
        <yMin>499</yMin>
        <xMax>605</xMax>
        <yMax>639</yMax>
      </defaultRect>
      <dialogue>Thank you so much for sharing this with me, Dave. I promise, the appropriate action will be taken. You've helped a lot of people today.</dialogue>
      <character>player</character>
      <expression>neutral</expression>
      <advancedOptions>false</advancedOptions>
      <characterAffected>player</characterAffected>
      <forceLeft>false</forceLeft>
      <longOption>false</longOption>
      <positive>false</positive>
      <negative>false</negative>
      <infoGathered>-1</infoGathered>
      <fired>false</fired>
      <restrictions>false</restrictions>
      <characterRestriction>player</characterRestriction>
      <positiveRestriction>99</positiveRestriction>
      <negativeRestriction>-99</negativeRestriction>
      <infoRestriction>-1</infoRestriction>
      <isDragged>false</isDragged>
      <isSelected>false</isSelected>
      <inPoint type="In">
        <id>59</id>
        <readyToInit>true</readyToInit>
        <rect>
          <x>343</x>
          <y>1132</y>
          <position>
            <x>343</x>
            <y>1132</y>
          </position>
          <center>
            <x>353</x>
            <y>1137</y>
          </center>
          <min>
            <x>343</x>
            <y>1132</y>
          </min>
          <max>
            <x>363</x>
            <y>1142</y>
          </max>
          <width>20</width>
          <height>10</height>
          <size>
            <x>20</x>
            <y>10</y>
          </size>
          <xMin>343</xMin>
          <yMin>1132</yMin>
          <xMax>363</xMax>
          <yMax>1142</yMax>
        </rect>
        <nodeRect>
          <x>253</x>
          <y>1137</y>
          <position>
            <x>253</x>
            <y>1137</y>
          </position>
          <center>
            <x>353</x>
            <y>1241</y>
          </center>
          <min>
            <x>253</x>
            <y>1137</y>
          </min>
          <max>
            <x>453</x>
            <y>1345</y>
          </max>
          <width>200</width>
          <height>208</height>
          <size>
            <x>200</x>
            <y>208</y>
          </size>
          <xMin>253</xMin>
          <yMin>1137</yMin>
          <xMax>453</xMax>
          <yMax>1345</yMax>
        </nodeRect>
      </inPoint>
      <outPoint type="Out">
        <id>59</id>
        <readyToInit>true</readyToInit>
        <rect>
          <x>343</x>
          <y>1338</y>
          <position>
            <x>343</x>
            <y>1338</y>
          </position>
          <center>
            <x>353</x>
            <y>1343</y>
          </center>
          <min>
            <x>343</x>
            <y>1338</y>
          </min>
          <max>
            <x>363</x>
            <y>1348</y>
          </max>
          <width>20</width>
          <height>10</height>
          <size>
            <x>20</x>
            <y>10</y>
          </size>
          <xMin>343</xMin>
          <yMin>1338</yMin>
          <xMax>363</xMax>
          <yMax>1348</yMax>
        </rect>
        <nodeRect>
          <x>253</x>
          <y>1137</y>
          <position>
            <x>253</x>
            <y>1137</y>
          </position>
          <center>
            <x>353</x>
            <y>1241</y>
          </center>
          <min>
            <x>253</x>
            <y>1137</y>
          </min>
          <max>
            <x>453</x>
            <y>1345</y>
          </max>
          <width>200</width>
          <height>208</height>
          <size>
            <x>200</x>
            <y>208</y>
          </size>
          <xMin>253</xMin>
          <yMin>1137</yMin>
          <xMax>453</xMax>
          <yMax>1345</yMax>
        </nodeRect>
      </outPoint>
    </DialogueNode>
    <DialogueNode>
      <id>60</id>
      <readyToInit>true</readyToInit>
      <rect>
        <x>252</x>
        <y>1393</y>
        <position>
          <x>252</x>
          <y>1393</y>
        </position>
        <center>
          <x>352</x>
          <y>1490.5</y>
        </center>
        <min>
          <x>252</x>
          <y>1393</y>
        </min>
        <max>
          <x>452</x>
          <y>1588</y>
        </max>
        <width>200</width>
        <height>195</height>
        <size>
          <x>200</x>
          <y>195</y>
        </size>
        <xMin>252</xMin>
        <yMin>1393</yMin>
        <xMax>452</xMax>
        <yMax>1588</yMax>
      </rect>
      <defaultRect>
        <x>318</x>
        <y>759</y>
        <position>
          <x>318</x>
          <y>759</y>
        </position>
        <center>
          <x>418</x>
          <y>829</y>
        </center>
        <min>
          <x>318</x>
          <y>759</y>
        </min>
        <max>
          <x>518</x>
          <y>899</y>
        </max>
        <width>200</width>
        <height>140</height>
        <size>
          <x>200</x>
          <y>140</y>
        </size>
        <xMin>318</xMin>
        <yMin>759</yMin>
        <xMax>518</xMax>
        <yMax>899</yMax>
      </defaultRect>
      <dialogue>Anytime. Let me know if there's anything else I can do to help. I really would like to see this office become a better place.</dialogue>
      <character>dave</character>
      <expression>neutral</expression>
      <advancedOptions>false</advancedOptions>
      <characterAffected>player</characterAffected>
      <forceLeft>false</forceLeft>
      <longOption>false</longOption>
      <positive>false</positive>
      <negative>false</negative>
      <infoGathered>-1</infoGathered>
      <fired>false</fired>
      <restrictions>false</restrictions>
      <characterRestriction>player</characterRestriction>
      <positiveRestriction>99</positiveRestriction>
      <negativeRestriction>-99</negativeRestriction>
      <infoRestriction>-1</infoRestriction>
      <isDragged>false</isDragged>
      <isSelected>false</isSelected>
      <inPoint type="In">
        <id>60</id>
        <readyToInit>true</readyToInit>
        <rect>
          <x>342</x>
          <y>1388</y>
          <position>
            <x>342</x>
            <y>1388</y>
          </position>
          <center>
            <x>352</x>
            <y>1393</y>
          </center>
          <min>
            <x>342</x>
            <y>1388</y>
          </min>
          <max>
            <x>362</x>
            <y>1398</y>
          </max>
          <width>20</width>
          <height>10</height>
          <size>
            <x>20</x>
            <y>10</y>
          </size>
          <xMin>342</xMin>
          <yMin>1388</yMin>
          <xMax>362</xMax>
          <yMax>1398</yMax>
        </rect>
        <nodeRect>
          <x>252</x>
          <y>1393</y>
          <position>
            <x>252</x>
            <y>1393</y>
          </position>
          <center>
            <x>352</x>
            <y>1490.5</y>
          </center>
          <min>
            <x>252</x>
            <y>1393</y>
          </min>
          <max>
            <x>452</x>
            <y>1588</y>
          </max>
          <width>200</width>
          <height>195</height>
          <size>
            <x>200</x>
            <y>195</y>
          </size>
          <xMin>252</xMin>
          <yMin>1393</yMin>
          <xMax>452</xMax>
          <yMax>1588</yMax>
        </nodeRect>
      </inPoint>
      <outPoint type="Out">
        <id>60</id>
        <readyToInit>true</readyToInit>
        <rect>
          <x>342</x>
          <y>1581</y>
          <position>
            <x>342</x>
            <y>1581</y>
          </position>
          <center>
            <x>352</x>
            <y>1586</y>
          </center>
          <min>
            <x>342</x>
            <y>1581</y>
          </min>
          <max>
            <x>362</x>
            <y>1591</y>
          </max>
          <width>20</width>
          <height>10</height>
          <size>
            <x>20</x>
            <y>10</y>
          </size>
          <xMin>342</xMin>
          <yMin>1581</yMin>
          <xMax>362</xMax>
          <yMax>1591</yMax>
        </rect>
        <nodeRect>
          <x>252</x>
          <y>1393</y>
          <position>
            <x>252</x>
            <y>1393</y>
          </position>
          <center>
            <x>352</x>
            <y>1490.5</y>
          </center>
          <min>
            <x>252</x>
            <y>1393</y>
          </min>
          <max>
            <x>452</x>
            <y>1588</y>
          </max>
          <width>200</width>
          <height>195</height>
          <size>
            <x>200</x>
            <y>195</y>
          </size>
          <xMin>252</xMin>
          <yMin>1393</yMin>
          <xMax>452</xMax>
          <yMax>1588</yMax>
        </nodeRect>
      </outPoint>
    </DialogueNode>
    <DialogueNode>
      <id>61</id>
      <readyToInit>true</readyToInit>
      <rect>
        <x>254</x>
        <y>1660</y>
        <position>
          <x>254</x>
          <y>1660</y>
        </position>
        <center>
          <x>354</x>
          <y>1814.5</y>
        </center>
        <min>
          <x>254</x>
          <y>1660</y>
        </min>
        <max>
          <x>454</x>
          <y>1969</y>
        </max>
        <width>200</width>
        <height>309</height>
        <size>
          <x>200</x>
          <y>309</y>
        </size>
        <xMin>254</xMin>
        <yMin>1660</yMin>
        <xMax>454</xMax>
        <yMax>1969</yMax>
      </rect>
      <defaultRect>
        <x>284</x>
        <y>602</y>
        <position>
          <x>284</x>
          <y>602</y>
        </position>
        <center>
          <x>384</x>
          <y>672</y>
        </center>
        <min>
          <x>284</x>
          <y>602</y>
        </min>
        <max>
          <x>484</x>
          <y>742</y>
        </max>
        <width>200</width>
        <height>140</height>
        <size>
          <x>200</x>
          <y>140</y>
        </size>
        <xMin>284</xMin>
        <yMin>602</yMin>
        <xMax>484</xMax>
        <yMax>742</yMax>
      </defaultRect>
      <dialogue>Me too, Dave. And it's going to be.</dialogue>
      <character>player</character>
      <expression>neutral</expression>
      <advancedOptions>true</advancedOptions>
      <characterAffected>stan</characterAffected>
      <forceLeft>false</forceLeft>
      <longOption>false</longOption>
      <positive>false</positive>
      <negative>false</negative>
      <infoGathered>1</infoGathered>
      <fired>false</fired>
      <restrictions>false</restrictions>
      <characterRestriction>player</characterRestriction>
      <positiveRestriction>99</positiveRestriction>
      <negativeRestriction>-99</negativeRestriction>
      <infoRestriction>-1</infoRestriction>
      <isDragged>false</isDragged>
      <isSelected>false</isSelected>
      <inPoint type="In">
        <id>61</id>
        <readyToInit>true</readyToInit>
        <rect>
          <x>344</x>
          <y>1655</y>
          <position>
            <x>344</x>
            <y>1655</y>
          </position>
          <center>
            <x>354</x>
            <y>1660</y>
          </center>
          <min>
            <x>344</x>
            <y>1655</y>
          </min>
          <max>
            <x>364</x>
            <y>1665</y>
          </max>
          <width>20</width>
          <height>10</height>
          <size>
            <x>20</x>
            <y>10</y>
          </size>
          <xMin>344</xMin>
          <yMin>1655</yMin>
          <xMax>364</xMax>
          <yMax>1665</yMax>
        </rect>
        <nodeRect>
          <x>254</x>
          <y>1660</y>
          <position>
            <x>254</x>
            <y>1660</y>
          </position>
          <center>
            <x>354</x>
            <y>1814.5</y>
          </center>
          <min>
            <x>254</x>
            <y>1660</y>
          </min>
          <max>
            <x>454</x>
            <y>1969</y>
          </max>
          <width>200</width>
          <height>309</height>
          <size>
            <x>200</x>
            <y>309</y>
          </size>
          <xMin>254</xMin>
          <yMin>1660</yMin>
          <xMax>454</xMax>
          <yMax>1969</yMax>
        </nodeRect>
      </inPoint>
      <outPoint type="Out">
        <id>61</id>
        <readyToInit>true</readyToInit>
        <rect>
          <x>344</x>
          <y>1962</y>
          <position>
            <x>344</x>
            <y>1962</y>
          </position>
          <center>
            <x>354</x>
            <y>1967</y>
          </center>
          <min>
            <x>344</x>
            <y>1962</y>
          </min>
          <max>
            <x>364</x>
            <y>1972</y>
          </max>
          <width>20</width>
          <height>10</height>
          <size>
            <x>20</x>
            <y>10</y>
          </size>
          <xMin>344</xMin>
          <yMin>1962</yMin>
          <xMax>364</xMax>
          <yMax>1972</yMax>
        </rect>
        <nodeRect>
          <x>254</x>
          <y>1660</y>
          <position>
            <x>254</x>
            <y>1660</y>
          </position>
          <center>
            <x>354</x>
            <y>1814.5</y>
          </center>
          <min>
            <x>254</x>
            <y>1660</y>
          </min>
          <max>
            <x>454</x>
            <y>1969</y>
          </max>
          <width>200</width>
          <height>309</height>
          <size>
            <x>200</x>
            <y>309</y>
          </size>
          <xMin>254</xMin>
          <yMin>1660</yMin>
          <xMax>454</xMax>
          <yMax>1969</yMax>
        </nodeRect>
      </outPoint>
    </DialogueNode>
  </Nodes>
  <Connections>
    <Connection>
      <readyToInit>true</readyToInit>
      <inPoint type="In">
        <id>56</id>
        <readyToInit>true</readyToInit>
        <rect>
          <x>339</x>
          <y>409</y>
          <position>
            <x>339</x>
            <y>409</y>
          </position>
          <center>
            <x>349</x>
            <y>414</y>
          </center>
          <min>
            <x>339</x>
            <y>409</y>
          </min>
          <max>
            <x>359</x>
            <y>419</y>
          </max>
          <width>20</width>
          <height>10</height>
          <size>
            <x>20</x>
            <y>10</y>
          </size>
          <xMin>339</xMin>
          <yMin>409</yMin>
          <xMax>359</xMax>
          <yMax>419</yMax>
        </rect>
        <nodeRect>
          <x>249</x>
          <y>414</y>
          <position>
            <x>249</x>
            <y>414</y>
          </position>
          <center>
            <x>349</x>
            <y>498.5</y>
          </center>
          <min>
            <x>249</x>
            <y>414</y>
          </min>
          <max>
            <x>449</x>
            <y>583</y>
          </max>
          <width>200</width>
          <height>169</height>
          <size>
            <x>200</x>
            <y>169</y>
          </size>
          <xMin>249</xMin>
          <yMin>414</yMin>
          <xMax>449</xMax>
          <yMax>583</yMax>
        </nodeRect>
      </inPoint>
      <outPoint type="Out">
        <id>54</id>
        <readyToInit>true</readyToInit>
        <rect>
          <x>339</x>
          <y>213</y>
          <position>
            <x>339</x>
            <y>213</y>
          </position>
          <center>
            <x>349</x>
            <y>218</y>
          </center>
          <min>
            <x>339</x>
            <y>213</y>
          </min>
          <max>
            <x>359</x>
            <y>223</y>
          </max>
          <width>20</width>
          <height>10</height>
          <size>
            <x>20</x>
            <y>10</y>
          </size>
          <xMin>339</xMin>
          <yMin>213</yMin>
          <xMax>359</xMax>
          <yMax>223</yMax>
        </rect>
        <nodeRect>
          <x>249</x>
          <y>38</y>
          <position>
            <x>249</x>
            <y>38</y>
          </position>
          <center>
            <x>349</x>
            <y>129</y>
          </center>
          <min>
            <x>249</x>
            <y>38</y>
          </min>
          <max>
            <x>449</x>
            <y>220</y>
          </max>
          <width>200</width>
          <height>182</height>
          <size>
            <x>200</x>
            <y>182</y>
          </size>
          <xMin>249</xMin>
          <yMin>38</yMin>
          <xMax>449</xMax>
          <yMax>220</yMax>
        </nodeRect>
      </outPoint>
    </Connection>
    <Connection>
      <readyToInit>true</readyToInit>
      <inPoint type="In">
        <id>57</id>
        <readyToInit>true</readyToInit>
        <rect>
          <x>340</x>
          <y>629</y>
          <position>
            <x>340</x>
            <y>629</y>
          </position>
          <center>
            <x>350</x>
            <y>634</y>
          </center>
          <min>
            <x>340</x>
            <y>629</y>
          </min>
          <max>
            <x>360</x>
            <y>639</y>
          </max>
          <width>20</width>
          <height>10</height>
          <size>
            <x>20</x>
            <y>10</y>
          </size>
          <xMin>340</xMin>
          <yMin>629</yMin>
          <xMax>360</xMax>
          <yMax>639</yMax>
        </rect>
        <nodeRect>
          <x>250</x>
          <y>634</y>
          <position>
            <x>250</x>
            <y>634</y>
          </position>
          <center>
            <x>350</x>
            <y>738</y>
          </center>
          <min>
            <x>250</x>
            <y>634</y>
          </min>
          <max>
            <x>450</x>
            <y>842</y>
          </max>
          <width>200</width>
          <height>208</height>
          <size>
            <x>200</x>
            <y>208</y>
          </size>
          <xMin>250</xMin>
          <yMin>634</yMin>
          <xMax>450</xMax>
          <yMax>842</yMax>
        </nodeRect>
      </inPoint>
      <outPoint type="Out">
        <id>56</id>
        <readyToInit>true</readyToInit>
        <rect>
          <x>339</x>
          <y>576</y>
          <position>
            <x>339</x>
            <y>576</y>
          </position>
          <center>
            <x>349</x>
            <y>581</y>
          </center>
          <min>
            <x>339</x>
            <y>576</y>
          </min>
          <max>
            <x>359</x>
            <y>586</y>
          </max>
          <width>20</width>
          <height>10</height>
          <size>
            <x>20</x>
            <y>10</y>
          </size>
          <xMin>339</xMin>
          <yMin>576</yMin>
          <xMax>359</xMax>
          <yMax>586</yMax>
        </rect>
        <nodeRect>
          <x>249</x>
          <y>414</y>
          <position>
            <x>249</x>
            <y>414</y>
          </position>
          <center>
            <x>349</x>
            <y>498.5</y>
          </center>
          <min>
            <x>249</x>
            <y>414</y>
          </min>
          <max>
            <x>449</x>
            <y>583</y>
          </max>
          <width>200</width>
          <height>169</height>
          <size>
            <x>200</x>
            <y>169</y>
          </size>
          <xMin>249</xMin>
          <yMin>414</yMin>
          <xMax>449</xMax>
          <yMax>583</yMax>
        </nodeRect>
      </outPoint>
    </Connection>
    <Connection>
      <readyToInit>true</readyToInit>
      <inPoint type="In">
        <id>58</id>
        <readyToInit>true</readyToInit>
        <rect>
          <x>342</x>
          <y>896</y>
          <position>
            <x>342</x>
            <y>896</y>
          </position>
          <center>
            <x>352</x>
            <y>901</y>
          </center>
          <min>
            <x>342</x>
            <y>896</y>
          </min>
          <max>
            <x>362</x>
            <y>906</y>
          </max>
          <width>20</width>
          <height>10</height>
          <size>
            <x>20</x>
            <y>10</y>
          </size>
          <xMin>342</xMin>
          <yMin>896</yMin>
          <xMax>362</xMax>
          <yMax>906</yMax>
        </rect>
        <nodeRect>
          <x>252</x>
          <y>901</y>
          <position>
            <x>252</x>
            <y>901</y>
          </position>
          <center>
            <x>352</x>
            <y>985.5</y>
          </center>
          <min>
            <x>252</x>
            <y>901</y>
          </min>
          <max>
            <x>452</x>
            <y>1070</y>
          </max>
          <width>200</width>
          <height>169</height>
          <size>
            <x>200</x>
            <y>169</y>
          </size>
          <xMin>252</xMin>
          <yMin>901</yMin>
          <xMax>452</xMax>
          <yMax>1070</yMax>
        </nodeRect>
      </inPoint>
      <outPoint type="Out">
        <id>57</id>
        <readyToInit>true</readyToInit>
        <rect>
          <x>340</x>
          <y>835</y>
          <position>
            <x>340</x>
            <y>835</y>
          </position>
          <center>
            <x>350</x>
            <y>840</y>
          </center>
          <min>
            <x>340</x>
            <y>835</y>
          </min>
          <max>
            <x>360</x>
            <y>845</y>
          </max>
          <width>20</width>
          <height>10</height>
          <size>
            <x>20</x>
            <y>10</y>
          </size>
          <xMin>340</xMin>
          <yMin>835</yMin>
          <xMax>360</xMax>
          <yMax>845</yMax>
        </rect>
        <nodeRect>
          <x>250</x>
          <y>634</y>
          <position>
            <x>250</x>
            <y>634</y>
          </position>
          <center>
            <x>350</x>
            <y>738</y>
          </center>
          <min>
            <x>250</x>
            <y>634</y>
          </min>
          <max>
            <x>450</x>
            <y>842</y>
          </max>
          <width>200</width>
          <height>208</height>
          <size>
            <x>200</x>
            <y>208</y>
          </size>
          <xMin>250</xMin>
          <yMin>634</yMin>
          <xMax>450</xMax>
          <yMax>842</yMax>
        </nodeRect>
      </outPoint>
    </Connection>
    <Connection>
      <readyToInit>true</readyToInit>
      <inPoint type="In">
        <id>59</id>
        <readyToInit>true</readyToInit>
        <rect>
          <x>343</x>
          <y>1132</y>
          <position>
            <x>343</x>
            <y>1132</y>
          </position>
          <center>
            <x>353</x>
            <y>1137</y>
          </center>
          <min>
            <x>343</x>
            <y>1132</y>
          </min>
          <max>
            <x>363</x>
            <y>1142</y>
          </max>
          <width>20</width>
          <height>10</height>
          <size>
            <x>20</x>
            <y>10</y>
          </size>
          <xMin>343</xMin>
          <yMin>1132</yMin>
          <xMax>363</xMax>
          <yMax>1142</yMax>
        </rect>
        <nodeRect>
          <x>253</x>
          <y>1137</y>
          <position>
            <x>253</x>
            <y>1137</y>
          </position>
          <center>
            <x>353</x>
            <y>1241</y>
          </center>
          <min>
            <x>253</x>
            <y>1137</y>
          </min>
          <max>
            <x>453</x>
            <y>1345</y>
          </max>
          <width>200</width>
          <height>208</height>
          <size>
            <x>200</x>
            <y>208</y>
          </size>
          <xMin>253</xMin>
          <yMin>1137</yMin>
          <xMax>453</xMax>
          <yMax>1345</yMax>
        </nodeRect>
      </inPoint>
      <outPoint type="Out">
        <id>58</id>
        <readyToInit>true</readyToInit>
        <rect>
          <x>342</x>
          <y>1063</y>
          <position>
            <x>342</x>
            <y>1063</y>
          </position>
          <center>
            <x>352</x>
            <y>1068</y>
          </center>
          <min>
            <x>342</x>
            <y>1063</y>
          </min>
          <max>
            <x>362</x>
            <y>1073</y>
          </max>
          <width>20</width>
          <height>10</height>
          <size>
            <x>20</x>
            <y>10</y>
          </size>
          <xMin>342</xMin>
          <yMin>1063</yMin>
          <xMax>362</xMax>
          <yMax>1073</yMax>
        </rect>
        <nodeRect>
          <x>252</x>
          <y>901</y>
          <position>
            <x>252</x>
            <y>901</y>
          </position>
          <center>
            <x>352</x>
            <y>985.5</y>
          </center>
          <min>
            <x>252</x>
            <y>901</y>
          </min>
          <max>
            <x>452</x>
            <y>1070</y>
          </max>
          <width>200</width>
          <height>169</height>
          <size>
            <x>200</x>
            <y>169</y>
          </size>
          <xMin>252</xMin>
          <yMin>901</yMin>
          <xMax>452</xMax>
          <yMax>1070</yMax>
        </nodeRect>
      </outPoint>
    </Connection>
    <Connection>
      <readyToInit>true</readyToInit>
      <inPoint type="In">
        <id>60</id>
        <readyToInit>true</readyToInit>
        <rect>
          <x>342</x>
          <y>1388</y>
          <position>
            <x>342</x>
            <y>1388</y>
          </position>
          <center>
            <x>352</x>
            <y>1393</y>
          </center>
          <min>
            <x>342</x>
            <y>1388</y>
          </min>
          <max>
            <x>362</x>
            <y>1398</y>
          </max>
          <width>20</width>
          <height>10</height>
          <size>
            <x>20</x>
            <y>10</y>
          </size>
          <xMin>342</xMin>
          <yMin>1388</yMin>
          <xMax>362</xMax>
          <yMax>1398</yMax>
        </rect>
        <nodeRect>
          <x>252</x>
          <y>1393</y>
          <position>
            <x>252</x>
            <y>1393</y>
          </position>
          <center>
            <x>352</x>
            <y>1490.5</y>
          </center>
          <min>
            <x>252</x>
            <y>1393</y>
          </min>
          <max>
            <x>452</x>
            <y>1588</y>
          </max>
          <width>200</width>
          <height>195</height>
          <size>
            <x>200</x>
            <y>195</y>
          </size>
          <xMin>252</xMin>
          <yMin>1393</yMin>
          <xMax>452</xMax>
          <yMax>1588</yMax>
        </nodeRect>
      </inPoint>
      <outPoint type="Out">
        <id>59</id>
        <readyToInit>true</readyToInit>
        <rect>
          <x>343</x>
          <y>1338</y>
          <position>
            <x>343</x>
            <y>1338</y>
          </position>
          <center>
            <x>353</x>
            <y>1343</y>
          </center>
          <min>
            <x>343</x>
            <y>1338</y>
          </min>
          <max>
            <x>363</x>
            <y>1348</y>
          </max>
          <width>20</width>
          <height>10</height>
          <size>
            <x>20</x>
            <y>10</y>
          </size>
          <xMin>343</xMin>
          <yMin>1338</yMin>
          <xMax>363</xMax>
          <yMax>1348</yMax>
        </rect>
        <nodeRect>
          <x>253</x>
          <y>1137</y>
          <position>
            <x>253</x>
            <y>1137</y>
          </position>
          <center>
            <x>353</x>
            <y>1241</y>
          </center>
          <min>
            <x>253</x>
            <y>1137</y>
          </min>
          <max>
            <x>453</x>
            <y>1345</y>
          </max>
          <width>200</width>
          <height>208</height>
          <size>
            <x>200</x>
            <y>208</y>
          </size>
          <xMin>253</xMin>
          <yMin>1137</yMin>
          <xMax>453</xMax>
          <yMax>1345</yMax>
        </nodeRect>
      </outPoint>
    </Connection>
    <Connection>
      <readyToInit>true</readyToInit>
      <inPoint type="In">
        <id>61</id>
        <readyToInit>true</readyToInit>
        <rect>
          <x>344</x>
          <y>1655</y>
          <position>
            <x>344</x>
            <y>1655</y>
          </position>
          <center>
            <x>354</x>
            <y>1660</y>
          </center>
          <min>
            <x>344</x>
            <y>1655</y>
          </min>
          <max>
            <x>364</x>
            <y>1665</y>
          </max>
          <width>20</width>
          <height>10</height>
          <size>
            <x>20</x>
            <y>10</y>
          </size>
          <xMin>344</xMin>
          <yMin>1655</yMin>
          <xMax>364</xMax>
          <yMax>1665</yMax>
        </rect>
        <nodeRect>
          <x>254</x>
          <y>1660</y>
          <position>
            <x>254</x>
            <y>1660</y>
          </position>
          <center>
            <x>354</x>
            <y>1814.5</y>
          </center>
          <min>
            <x>254</x>
            <y>1660</y>
          </min>
          <max>
            <x>454</x>
            <y>1969</y>
          </max>
          <width>200</width>
          <height>309</height>
          <size>
            <x>200</x>
            <y>309</y>
          </size>
          <xMin>254</xMin>
          <yMin>1660</yMin>
          <xMax>454</xMax>
          <yMax>1969</yMax>
        </nodeRect>
      </inPoint>
      <outPoint type="Out">
        <id>60</id>
        <readyToInit>true</readyToInit>
        <rect>
          <x>342</x>
          <y>1581</y>
          <position>
            <x>342</x>
            <y>1581</y>
          </position>
          <center>
            <x>352</x>
            <y>1586</y>
          </center>
          <min>
            <x>342</x>
            <y>1581</y>
          </min>
          <max>
            <x>362</x>
            <y>1591</y>
          </max>
          <width>20</width>
          <height>10</height>
          <size>
            <x>20</x>
            <y>10</y>
          </size>
          <xMin>342</xMin>
          <yMin>1581</yMin>
          <xMax>362</xMax>
          <yMax>1591</yMax>
        </rect>
        <nodeRect>
          <x>252</x>
          <y>1393</y>
          <position>
            <x>252</x>
            <y>1393</y>
          </position>
          <center>
            <x>352</x>
            <y>1490.5</y>
          </center>
          <min>
            <x>252</x>
            <y>1393</y>
          </min>
          <max>
            <x>452</x>
            <y>1588</y>
          </max>
          <width>200</width>
          <height>195</height>
          <size>
            <x>200</x>
            <y>195</y>
          </size>
          <xMin>252</xMin>
          <yMin>1393</yMin>
          <xMax>452</xMax>
          <yMax>1588</yMax>
        </nodeRect>
      </outPoint>
    </Connection>
  </Connections>
</DialogueTree>