<?xml version="1.0" encoding="utf-8"?>
<DialogueTree>
  <Nodes>
    <DialogueNode>
      <id>4</id>
      <readyToInit>true</readyToInit>
      <rect>
        <x>517</x>
        <y>-321</y>
        <position>
          <x>517</x>
          <y>-321</y>
        </position>
        <center>
          <x>617</x>
          <y>-230</y>
        </center>
        <min>
          <x>517</x>
          <y>-321</y>
        </min>
        <max>
          <x>717</x>
          <y>-139</y>
        </max>
        <width>200</width>
        <height>182</height>
        <size>
          <x>200</x>
          <y>182</y>
        </size>
        <xMin>517</xMin>
        <yMin>-321</yMin>
        <xMax>717</xMax>
        <yMax>-139</yMax>
      </rect>
      <defaultRect>
        <x>62</x>
        <y>172</y>
        <position>
          <x>62</x>
          <y>172</y>
        </position>
        <center>
          <x>162</x>
          <y>242</y>
        </center>
        <min>
          <x>62</x>
          <y>172</y>
        </min>
        <max>
          <x>262</x>
          <y>312</y>
        </max>
        <width>200</width>
        <height>140</height>
        <size>
          <x>200</x>
          <y>140</y>
        </size>
        <xMin>62</xMin>
        <yMin>172</yMin>
        <xMax>262</xMax>
        <yMax>312</yMax>
      </defaultRect>
      <dialogue>Richard has me working on a critical assignment that needs to be done by tomorrow. </dialogue>
      <character>stan</character>
      <expression>neutral</expression>
      <advancedOptions>false</advancedOptions>
      <characterAffected>player</characterAffected>
      <forceLeft>false</forceLeft>
      <longOption>false</longOption>
      <positive>false</positive>
      <negative>false</negative>
      <infoGathered>-1</infoGathered>
      <fired>false</fired>
      <restrictions>false</restrictions>
      <characterRestriction>player</characterRestriction>
      <positiveRestriction>99</positiveRestriction>
      <negativeRestriction>-99</negativeRestriction>
      <infoRestriction>-1</infoRestriction>
      <isDragged>false</isDragged>
      <isSelected>false</isSelected>
      <inPoint type="In">
        <id>4</id>
        <readyToInit>true</readyToInit>
        <rect>
          <x>607</x>
          <y>-326</y>
          <position>
            <x>607</x>
            <y>-326</y>
          </position>
          <center>
            <x>617</x>
            <y>-321</y>
          </center>
          <min>
            <x>607</x>
            <y>-326</y>
          </min>
          <max>
            <x>627</x>
            <y>-316</y>
          </max>
          <width>20</width>
          <height>10</height>
          <size>
            <x>20</x>
            <y>10</y>
          </size>
          <xMin>607</xMin>
          <yMin>-326</yMin>
          <xMax>627</xMax>
          <yMax>-316</yMax>
        </rect>
        <nodeRect>
          <x>517</x>
          <y>-321</y>
          <position>
            <x>517</x>
            <y>-321</y>
          </position>
          <center>
            <x>617</x>
            <y>-230</y>
          </center>
          <min>
            <x>517</x>
            <y>-321</y>
          </min>
          <max>
            <x>717</x>
            <y>-139</y>
          </max>
          <width>200</width>
          <height>182</height>
          <size>
            <x>200</x>
            <y>182</y>
          </size>
          <xMin>517</xMin>
          <yMin>-321</yMin>
          <xMax>717</xMax>
          <yMax>-139</yMax>
        </nodeRect>
      </inPoint>
      <outPoint type="Out">
        <id>4</id>
        <readyToInit>true</readyToInit>
        <rect>
          <x>607</x>
          <y>-146</y>
          <position>
            <x>607</x>
            <y>-146</y>
          </position>
          <center>
            <x>617</x>
            <y>-141</y>
          </center>
          <min>
            <x>607</x>
            <y>-146</y>
          </min>
          <max>
            <x>627</x>
            <y>-136</y>
          </max>
          <width>20</width>
          <height>10</height>
          <size>
            <x>20</x>
            <y>10</y>
          </size>
          <xMin>607</xMin>
          <yMin>-146</yMin>
          <xMax>627</xMax>
          <yMax>-136</yMax>
        </rect>
        <nodeRect>
          <x>517</x>
          <y>-321</y>
          <position>
            <x>517</x>
            <y>-321</y>
          </position>
          <center>
            <x>617</x>
            <y>-230</y>
          </center>
          <min>
            <x>517</x>
            <y>-321</y>
          </min>
          <max>
            <x>717</x>
            <y>-139</y>
          </max>
          <width>200</width>
          <height>182</height>
          <size>
            <x>200</x>
            <y>182</y>
          </size>
          <xMin>517</xMin>
          <yMin>-321</yMin>
          <xMax>717</xMax>
          <yMax>-139</yMax>
        </nodeRect>
      </outPoint>
    </DialogueNode>
    <DialogueNode>
      <id>134</id>
      <readyToInit>true</readyToInit>
      <rect>
        <x>518</x>
        <y>-532</y>
        <position>
          <x>518</x>
          <y>-532</y>
        </position>
        <center>
          <x>618</x>
          <y>-454</y>
        </center>
        <min>
          <x>518</x>
          <y>-532</y>
        </min>
        <max>
          <x>718</x>
          <y>-376</y>
        </max>
        <width>200</width>
        <height>156</height>
        <size>
          <x>200</x>
          <y>156</y>
        </size>
        <xMin>518</xMin>
        <yMin>-532</yMin>
        <xMax>718</xMax>
        <yMax>-376</yMax>
      </rect>
      <defaultRect>
        <x>470</x>
        <y>48</y>
        <position>
          <x>470</x>
          <y>48</y>
        </position>
        <center>
          <x>570</x>
          <y>118</y>
        </center>
        <min>
          <x>470</x>
          <y>48</y>
        </min>
        <max>
          <x>670</x>
          <y>188</y>
        </max>
        <width>200</width>
        <height>140</height>
        <size>
          <x>200</x>
          <y>140</y>
        </size>
        <xMin>470</xMin>
        <yMin>48</yMin>
        <xMax>670</xMax>
        <yMax>188</yMax>
      </defaultRect>
      <dialogue>Hey Stan, what are you up to?</dialogue>
      <character>player</character>
      <expression>neutral</expression>
      <advancedOptions>false</advancedOptions>
      <characterAffected>player</characterAffected>
      <forceLeft>false</forceLeft>
      <longOption>false</longOption>
      <positive>false</positive>
      <negative>false</negative>
      <infoGathered>-1</infoGathered>
      <fired>false</fired>
      <restrictions>false</restrictions>
      <characterRestriction>player</characterRestriction>
      <positiveRestriction>99</positiveRestriction>
      <negativeRestriction>-99</negativeRestriction>
      <infoRestriction>-1</infoRestriction>
      <isDragged>false</isDragged>
      <isSelected>false</isSelected>
      <inPoint type="In">
        <id>134</id>
        <readyToInit>true</readyToInit>
        <rect>
          <x>608</x>
          <y>-537</y>
          <position>
            <x>608</x>
            <y>-537</y>
          </position>
          <center>
            <x>618</x>
            <y>-532</y>
          </center>
          <min>
            <x>608</x>
            <y>-537</y>
          </min>
          <max>
            <x>628</x>
            <y>-527</y>
          </max>
          <width>20</width>
          <height>10</height>
          <size>
            <x>20</x>
            <y>10</y>
          </size>
          <xMin>608</xMin>
          <yMin>-537</yMin>
          <xMax>628</xMax>
          <yMax>-527</yMax>
        </rect>
        <nodeRect>
          <x>518</x>
          <y>-532</y>
          <position>
            <x>518</x>
            <y>-532</y>
          </position>
          <center>
            <x>618</x>
            <y>-454</y>
          </center>
          <min>
            <x>518</x>
            <y>-532</y>
          </min>
          <max>
            <x>718</x>
            <y>-376</y>
          </max>
          <width>200</width>
          <height>156</height>
          <size>
            <x>200</x>
            <y>156</y>
          </size>
          <xMin>518</xMin>
          <yMin>-532</yMin>
          <xMax>718</xMax>
          <yMax>-376</yMax>
        </nodeRect>
      </inPoint>
      <outPoint type="Out">
        <id>134</id>
        <readyToInit>true</readyToInit>
        <rect>
          <x>608</x>
          <y>-383</y>
          <position>
            <x>608</x>
            <y>-383</y>
          </position>
          <center>
            <x>618</x>
            <y>-378</y>
          </center>
          <min>
            <x>608</x>
            <y>-383</y>
          </min>
          <max>
            <x>628</x>
            <y>-373</y>
          </max>
          <width>20</width>
          <height>10</height>
          <size>
            <x>20</x>
            <y>10</y>
          </size>
          <xMin>608</xMin>
          <yMin>-383</yMin>
          <xMax>628</xMax>
          <yMax>-373</yMax>
        </rect>
        <nodeRect>
          <x>518</x>
          <y>-532</y>
          <position>
            <x>518</x>
            <y>-532</y>
          </position>
          <center>
            <x>618</x>
            <y>-454</y>
          </center>
          <min>
            <x>518</x>
            <y>-532</y>
          </min>
          <max>
            <x>718</x>
            <y>-376</y>
          </max>
          <width>200</width>
          <height>156</height>
          <size>
            <x>200</x>
            <y>156</y>
          </size>
          <xMin>518</xMin>
          <yMin>-532</yMin>
          <xMax>718</xMax>
          <yMax>-376</yMax>
        </nodeRect>
      </outPoint>
    </DialogueNode>
    <DialogueNode>
      <id>135</id>
      <readyToInit>true</readyToInit>
      <rect>
        <x>519</x>
        <y>-83</y>
        <position>
          <x>519</x>
          <y>-83</y>
        </position>
        <center>
          <x>619</x>
          <y>8</y>
        </center>
        <min>
          <x>519</x>
          <y>-83</y>
        </min>
        <max>
          <x>719</x>
          <y>99</y>
        </max>
        <width>200</width>
        <height>182</height>
        <size>
          <x>200</x>
          <y>182</y>
        </size>
        <xMin>519</xMin>
        <yMin>-83</yMin>
        <xMax>719</xMax>
        <yMax>99</yMax>
      </rect>
      <defaultRect>
        <x>466</x>
        <y>607</y>
        <position>
          <x>466</x>
          <y>607</y>
        </position>
        <center>
          <x>566</x>
          <y>677</y>
        </center>
        <min>
          <x>466</x>
          <y>607</y>
        </min>
        <max>
          <x>666</x>
          <y>747</y>
        </max>
        <width>200</width>
        <height>140</height>
        <size>
          <x>200</x>
          <y>140</y>
        </size>
        <xMin>466</xMin>
        <yMin>607</yMin>
        <xMax>666</xMax>
        <yMax>747</yMax>
      </defaultRect>
      <dialogue>It's no wonder, it's not like most of the other members of this office would be up to the task. </dialogue>
      <character>stan</character>
      <expression>neutral</expression>
      <advancedOptions>false</advancedOptions>
      <characterAffected>player</characterAffected>
      <forceLeft>false</forceLeft>
      <longOption>false</longOption>
      <positive>false</positive>
      <negative>false</negative>
      <infoGathered>-1</infoGathered>
      <fired>false</fired>
      <restrictions>false</restrictions>
      <characterRestriction>player</characterRestriction>
      <positiveRestriction>99</positiveRestriction>
      <negativeRestriction>-99</negativeRestriction>
      <infoRestriction>-1</infoRestriction>
      <isDragged>false</isDragged>
      <isSelected>false</isSelected>
      <inPoint type="In">
        <id>135</id>
        <readyToInit>true</readyToInit>
        <rect>
          <x>609</x>
          <y>-88</y>
          <position>
            <x>609</x>
            <y>-88</y>
          </position>
          <center>
            <x>619</x>
            <y>-83</y>
          </center>
          <min>
            <x>609</x>
            <y>-88</y>
          </min>
          <max>
            <x>629</x>
            <y>-78</y>
          </max>
          <width>20</width>
          <height>10</height>
          <size>
            <x>20</x>
            <y>10</y>
          </size>
          <xMin>609</xMin>
          <yMin>-88</yMin>
          <xMax>629</xMax>
          <yMax>-78</yMax>
        </rect>
        <nodeRect>
          <x>519</x>
          <y>-83</y>
          <position>
            <x>519</x>
            <y>-83</y>
          </position>
          <center>
            <x>619</x>
            <y>8</y>
          </center>
          <min>
            <x>519</x>
            <y>-83</y>
          </min>
          <max>
            <x>719</x>
            <y>99</y>
          </max>
          <width>200</width>
          <height>182</height>
          <size>
            <x>200</x>
            <y>182</y>
          </size>
          <xMin>519</xMin>
          <yMin>-83</yMin>
          <xMax>719</xMax>
          <yMax>99</yMax>
        </nodeRect>
      </inPoint>
      <outPoint type="Out">
        <id>135</id>
        <readyToInit>true</readyToInit>
        <rect>
          <x>609</x>
          <y>92</y>
          <position>
            <x>609</x>
            <y>92</y>
          </position>
          <center>
            <x>619</x>
            <y>97</y>
          </center>
          <min>
            <x>609</x>
            <y>92</y>
          </min>
          <max>
            <x>629</x>
            <y>102</y>
          </max>
          <width>20</width>
          <height>10</height>
          <size>
            <x>20</x>
            <y>10</y>
          </size>
          <xMin>609</xMin>
          <yMin>92</yMin>
          <xMax>629</xMax>
          <yMax>102</yMax>
        </rect>
        <nodeRect>
          <x>519</x>
          <y>-83</y>
          <position>
            <x>519</x>
            <y>-83</y>
          </position>
          <center>
            <x>619</x>
            <y>8</y>
          </center>
          <min>
            <x>519</x>
            <y>-83</y>
          </min>
          <max>
            <x>719</x>
            <y>99</y>
          </max>
          <width>200</width>
          <height>182</height>
          <size>
            <x>200</x>
            <y>182</y>
          </size>
          <xMin>519</xMin>
          <yMin>-83</yMin>
          <xMax>719</xMax>
          <yMax>99</yMax>
        </nodeRect>
      </outPoint>
    </DialogueNode>
    <DialogueNode>
      <id>136</id>
      <readyToInit>true</readyToInit>
      <rect>
        <x>524</x>
        <y>321</y>
        <position>
          <x>524</x>
          <y>321</y>
        </position>
        <center>
          <x>624</x>
          <y>405.5</y>
        </center>
        <min>
          <x>524</x>
          <y>321</y>
        </min>
        <max>
          <x>724</x>
          <y>490</y>
        </max>
        <width>200</width>
        <height>169</height>
        <size>
          <x>200</x>
          <y>169</y>
        </size>
        <xMin>524</xMin>
        <yMin>321</yMin>
        <xMax>724</xMax>
        <yMax>490</yMax>
      </rect>
      <defaultRect>
        <x>523</x>
        <y>448</y>
        <position>
          <x>523</x>
          <y>448</y>
        </position>
        <center>
          <x>623</x>
          <y>518</y>
        </center>
        <min>
          <x>523</x>
          <y>448</y>
        </min>
        <max>
          <x>723</x>
          <y>588</y>
        </max>
        <width>200</width>
        <height>140</height>
        <size>
          <x>200</x>
          <y>140</y>
        </size>
        <xMin>523</xMin>
        <yMin>448</yMin>
        <xMax>723</xMax>
        <yMax>588</yMax>
      </defaultRect>
      <dialogue>Sorry, have a lot of work to do. Not time for chit chat. </dialogue>
      <character>stan</character>
      <expression>neutral</expression>
      <advancedOptions>false</advancedOptions>
      <characterAffected>player</characterAffected>
      <forceLeft>false</forceLeft>
      <longOption>false</longOption>
      <positive>false</positive>
      <negative>false</negative>
      <infoGathered>-1</infoGathered>
      <fired>false</fired>
      <restrictions>false</restrictions>
      <characterRestriction>player</characterRestriction>
      <positiveRestriction>99</positiveRestriction>
      <negativeRestriction>-99</negativeRestriction>
      <infoRestriction>-1</infoRestriction>
      <isDragged>false</isDragged>
      <isSelected>false</isSelected>
      <inPoint type="In">
        <id>136</id>
        <readyToInit>true</readyToInit>
        <rect>
          <x>614</x>
          <y>316</y>
          <position>
            <x>614</x>
            <y>316</y>
          </position>
          <center>
            <x>624</x>
            <y>321</y>
          </center>
          <min>
            <x>614</x>
            <y>316</y>
          </min>
          <max>
            <x>634</x>
            <y>326</y>
          </max>
          <width>20</width>
          <height>10</height>
          <size>
            <x>20</x>
            <y>10</y>
          </size>
          <xMin>614</xMin>
          <yMin>316</yMin>
          <xMax>634</xMax>
          <yMax>326</yMax>
        </rect>
        <nodeRect>
          <x>524</x>
          <y>321</y>
          <position>
            <x>524</x>
            <y>321</y>
          </position>
          <center>
            <x>624</x>
            <y>405.5</y>
          </center>
          <min>
            <x>524</x>
            <y>321</y>
          </min>
          <max>
            <x>724</x>
            <y>490</y>
          </max>
          <width>200</width>
          <height>169</height>
          <size>
            <x>200</x>
            <y>169</y>
          </size>
          <xMin>524</xMin>
          <yMin>321</yMin>
          <xMax>724</xMax>
          <yMax>490</yMax>
        </nodeRect>
      </inPoint>
      <outPoint type="Out">
        <id>136</id>
        <readyToInit>true</readyToInit>
        <rect>
          <x>614</x>
          <y>483</y>
          <position>
            <x>614</x>
            <y>483</y>
          </position>
          <center>
            <x>624</x>
            <y>488</y>
          </center>
          <min>
            <x>614</x>
            <y>483</y>
          </min>
          <max>
            <x>634</x>
            <y>493</y>
          </max>
          <width>20</width>
          <height>10</height>
          <size>
            <x>20</x>
            <y>10</y>
          </size>
          <xMin>614</xMin>
          <yMin>483</yMin>
          <xMax>634</xMax>
          <yMax>493</yMax>
        </rect>
        <nodeRect>
          <x>524</x>
          <y>321</y>
          <position>
            <x>524</x>
            <y>321</y>
          </position>
          <center>
            <x>624</x>
            <y>405.5</y>
          </center>
          <min>
            <x>524</x>
            <y>321</y>
          </min>
          <max>
            <x>724</x>
            <y>490</y>
          </max>
          <width>200</width>
          <height>169</height>
          <size>
            <x>200</x>
            <y>169</y>
          </size>
          <xMin>524</xMin>
          <yMin>321</yMin>
          <xMax>724</xMax>
          <yMax>490</yMax>
        </nodeRect>
      </outPoint>
    </DialogueNode>
    <DialogueNode>
      <id>137</id>
      <readyToInit>true</readyToInit>
      <rect>
        <x>523</x>
        <y>129</y>
        <position>
          <x>523</x>
          <y>129</y>
        </position>
        <center>
          <x>623</x>
          <y>207</y>
        </center>
        <min>
          <x>523</x>
          <y>129</y>
        </min>
        <max>
          <x>723</x>
          <y>285</y>
        </max>
        <width>200</width>
        <height>156</height>
        <size>
          <x>200</x>
          <y>156</y>
        </size>
        <xMin>523</xMin>
        <yMin>129</yMin>
        <xMax>723</xMax>
        <yMax>285</yMax>
      </rect>
      <defaultRect>
        <x>523</x>
        <y>426</y>
        <position>
          <x>523</x>
          <y>426</y>
        </position>
        <center>
          <x>623</x>
          <y>496</y>
        </center>
        <min>
          <x>523</x>
          <y>426</y>
        </min>
        <max>
          <x>723</x>
          <y>566</y>
        </max>
        <width>200</width>
        <height>140</height>
        <size>
          <x>200</x>
          <y>140</y>
        </size>
        <xMin>523</xMin>
        <yMin>426</yMin>
        <xMax>723</xMax>
        <yMax>566</yMax>
      </defaultRect>
      <dialogue>That's not- </dialogue>
      <character>player</character>
      <expression>angry</expression>
      <advancedOptions>false</advancedOptions>
      <characterAffected>player</characterAffected>
      <forceLeft>false</forceLeft>
      <longOption>false</longOption>
      <positive>false</positive>
      <negative>false</negative>
      <infoGathered>-1</infoGathered>
      <fired>false</fired>
      <restrictions>false</restrictions>
      <characterRestriction>player</characterRestriction>
      <positiveRestriction>99</positiveRestriction>
      <negativeRestriction>-99</negativeRestriction>
      <infoRestriction>-1</infoRestriction>
      <isDragged>false</isDragged>
      <isSelected>false</isSelected>
      <inPoint type="In">
        <id>137</id>
        <readyToInit>true</readyToInit>
        <rect>
          <x>613</x>
          <y>124</y>
          <position>
            <x>613</x>
            <y>124</y>
          </position>
          <center>
            <x>623</x>
            <y>129</y>
          </center>
          <min>
            <x>613</x>
            <y>124</y>
          </min>
          <max>
            <x>633</x>
            <y>134</y>
          </max>
          <width>20</width>
          <height>10</height>
          <size>
            <x>20</x>
            <y>10</y>
          </size>
          <xMin>613</xMin>
          <yMin>124</yMin>
          <xMax>633</xMax>
          <yMax>134</yMax>
        </rect>
        <nodeRect>
          <x>523</x>
          <y>129</y>
          <position>
            <x>523</x>
            <y>129</y>
          </position>
          <center>
            <x>623</x>
            <y>207</y>
          </center>
          <min>
            <x>523</x>
            <y>129</y>
          </min>
          <max>
            <x>723</x>
            <y>285</y>
          </max>
          <width>200</width>
          <height>156</height>
          <size>
            <x>200</x>
            <y>156</y>
          </size>
          <xMin>523</xMin>
          <yMin>129</yMin>
          <xMax>723</xMax>
          <yMax>285</yMax>
        </nodeRect>
      </inPoint>
      <outPoint type="Out">
        <id>137</id>
        <readyToInit>true</readyToInit>
        <rect>
          <x>613</x>
          <y>278</y>
          <position>
            <x>613</x>
            <y>278</y>
          </position>
          <center>
            <x>623</x>
            <y>283</y>
          </center>
          <min>
            <x>613</x>
            <y>278</y>
          </min>
          <max>
            <x>633</x>
            <y>288</y>
          </max>
          <width>20</width>
          <height>10</height>
          <size>
            <x>20</x>
            <y>10</y>
          </size>
          <xMin>613</xMin>
          <yMin>278</yMin>
          <xMax>633</xMax>
          <yMax>288</yMax>
        </rect>
        <nodeRect>
          <x>523</x>
          <y>129</y>
          <position>
            <x>523</x>
            <y>129</y>
          </position>
          <center>
            <x>623</x>
            <y>207</y>
          </center>
          <min>
            <x>523</x>
            <y>129</y>
          </min>
          <max>
            <x>723</x>
            <y>285</y>
          </max>
          <width>200</width>
          <height>156</height>
          <size>
            <x>200</x>
            <y>156</y>
          </size>
          <xMin>523</xMin>
          <yMin>129</yMin>
          <xMax>723</xMax>
          <yMax>285</yMax>
        </nodeRect>
      </outPoint>
    </DialogueNode>
    <DialogueNode>
      <id>138</id>
      <readyToInit>true</readyToInit>
      <rect>
        <x>529</x>
        <y>582</y>
        <position>
          <x>529</x>
          <y>582</y>
        </position>
        <center>
          <x>629</x>
          <y>660</y>
        </center>
        <min>
          <x>529</x>
          <y>582</y>
        </min>
        <max>
          <x>729</x>
          <y>738</y>
        </max>
        <width>200</width>
        <height>156</height>
        <size>
          <x>200</x>
          <y>156</y>
        </size>
        <xMin>529</xMin>
        <yMin>582</yMin>
        <xMax>729</xMax>
        <yMax>738</yMax>
      </rect>
      <defaultRect>
        <x>529</x>
        <y>582</y>
        <position>
          <x>529</x>
          <y>582</y>
        </position>
        <center>
          <x>629</x>
          <y>652</y>
        </center>
        <min>
          <x>529</x>
          <y>582</y>
        </min>
        <max>
          <x>729</x>
          <y>722</y>
        </max>
        <width>200</width>
        <height>140</height>
        <size>
          <x>200</x>
          <y>140</y>
        </size>
        <xMin>529</xMin>
        <yMin>582</yMin>
        <xMax>729</xMax>
        <yMax>722</yMax>
      </defaultRect>
      <dialogue>...</dialogue>
      <character>player</character>
      <expression>angry</expression>
      <advancedOptions>false</advancedOptions>
      <characterAffected>player</characterAffected>
      <forceLeft>false</forceLeft>
      <longOption>false</longOption>
      <positive>false</positive>
      <negative>false</negative>
      <infoGathered>-1</infoGathered>
      <fired>false</fired>
      <restrictions>false</restrictions>
      <characterRestriction>player</characterRestriction>
      <positiveRestriction>99</positiveRestriction>
      <negativeRestriction>-99</negativeRestriction>
      <infoRestriction>-1</infoRestriction>
      <isDragged>false</isDragged>
      <isSelected>false</isSelected>
      <inPoint type="In">
        <id>138</id>
        <readyToInit>true</readyToInit>
        <rect>
          <x>619</x>
          <y>577</y>
          <position>
            <x>619</x>
            <y>577</y>
          </position>
          <center>
            <x>629</x>
            <y>582</y>
          </center>
          <min>
            <x>619</x>
            <y>577</y>
          </min>
          <max>
            <x>639</x>
            <y>587</y>
          </max>
          <width>20</width>
          <height>10</height>
          <size>
            <x>20</x>
            <y>10</y>
          </size>
          <xMin>619</xMin>
          <yMin>577</yMin>
          <xMax>639</xMax>
          <yMax>587</yMax>
        </rect>
        <nodeRect>
          <x>529</x>
          <y>582</y>
          <position>
            <x>529</x>
            <y>582</y>
          </position>
          <center>
            <x>629</x>
            <y>660</y>
          </center>
          <min>
            <x>529</x>
            <y>582</y>
          </min>
          <max>
            <x>729</x>
            <y>738</y>
          </max>
          <width>200</width>
          <height>156</height>
          <size>
            <x>200</x>
            <y>156</y>
          </size>
          <xMin>529</xMin>
          <yMin>582</yMin>
          <xMax>729</xMax>
          <yMax>738</yMax>
        </nodeRect>
      </inPoint>
      <outPoint type="Out">
        <id>138</id>
        <readyToInit>true</readyToInit>
        <rect>
          <x>619</x>
          <y>731</y>
          <position>
            <x>619</x>
            <y>731</y>
          </position>
          <center>
            <x>629</x>
            <y>736</y>
          </center>
          <min>
            <x>619</x>
            <y>731</y>
          </min>
          <max>
            <x>639</x>
            <y>741</y>
          </max>
          <width>20</width>
          <height>10</height>
          <size>
            <x>20</x>
            <y>10</y>
          </size>
          <xMin>619</xMin>
          <yMin>731</yMin>
          <xMax>639</xMax>
          <yMax>741</yMax>
        </rect>
        <nodeRect>
          <x>529</x>
          <y>582</y>
          <position>
            <x>529</x>
            <y>582</y>
          </position>
          <center>
            <x>629</x>
            <y>660</y>
          </center>
          <min>
            <x>529</x>
            <y>582</y>
          </min>
          <max>
            <x>729</x>
            <y>738</y>
          </max>
          <width>200</width>
          <height>156</height>
          <size>
            <x>200</x>
            <y>156</y>
          </size>
          <xMin>529</xMin>
          <yMin>582</yMin>
          <xMax>729</xMax>
          <yMax>738</yMax>
        </nodeRect>
      </outPoint>
    </DialogueNode>
  </Nodes>
  <Connections>
    <Connection>
      <readyToInit>true</readyToInit>
      <inPoint type="In">
        <id>4</id>
        <readyToInit>true</readyToInit>
        <rect>
          <x>607</x>
          <y>-326</y>
          <position>
            <x>607</x>
            <y>-326</y>
          </position>
          <center>
            <x>617</x>
            <y>-321</y>
          </center>
          <min>
            <x>607</x>
            <y>-326</y>
          </min>
          <max>
            <x>627</x>
            <y>-316</y>
          </max>
          <width>20</width>
          <height>10</height>
          <size>
            <x>20</x>
            <y>10</y>
          </size>
          <xMin>607</xMin>
          <yMin>-326</yMin>
          <xMax>627</xMax>
          <yMax>-316</yMax>
        </rect>
        <nodeRect>
          <x>517</x>
          <y>-321</y>
          <position>
            <x>517</x>
            <y>-321</y>
          </position>
          <center>
            <x>617</x>
            <y>-230</y>
          </center>
          <min>
            <x>517</x>
            <y>-321</y>
          </min>
          <max>
            <x>717</x>
            <y>-139</y>
          </max>
          <width>200</width>
          <height>182</height>
          <size>
            <x>200</x>
            <y>182</y>
          </size>
          <xMin>517</xMin>
          <yMin>-321</yMin>
          <xMax>717</xMax>
          <yMax>-139</yMax>
        </nodeRect>
      </inPoint>
      <outPoint type="Out">
        <id>134</id>
        <readyToInit>true</readyToInit>
        <rect>
          <x>608</x>
          <y>-383</y>
          <position>
            <x>608</x>
            <y>-383</y>
          </position>
          <center>
            <x>618</x>
            <y>-378</y>
          </center>
          <min>
            <x>608</x>
            <y>-383</y>
          </min>
          <max>
            <x>628</x>
            <y>-373</y>
          </max>
          <width>20</width>
          <height>10</height>
          <size>
            <x>20</x>
            <y>10</y>
          </size>
          <xMin>608</xMin>
          <yMin>-383</yMin>
          <xMax>628</xMax>
          <yMax>-373</yMax>
        </rect>
        <nodeRect>
          <x>518</x>
          <y>-532</y>
          <position>
            <x>518</x>
            <y>-532</y>
          </position>
          <center>
            <x>618</x>
            <y>-454</y>
          </center>
          <min>
            <x>518</x>
            <y>-532</y>
          </min>
          <max>
            <x>718</x>
            <y>-376</y>
          </max>
          <width>200</width>
          <height>156</height>
          <size>
            <x>200</x>
            <y>156</y>
          </size>
          <xMin>518</xMin>
          <yMin>-532</yMin>
          <xMax>718</xMax>
          <yMax>-376</yMax>
        </nodeRect>
      </outPoint>
    </Connection>
    <Connection>
      <readyToInit>true</readyToInit>
      <inPoint type="In">
        <id>135</id>
        <readyToInit>true</readyToInit>
        <rect>
          <x>609</x>
          <y>-88</y>
          <position>
            <x>609</x>
            <y>-88</y>
          </position>
          <center>
            <x>619</x>
            <y>-83</y>
          </center>
          <min>
            <x>609</x>
            <y>-88</y>
          </min>
          <max>
            <x>629</x>
            <y>-78</y>
          </max>
          <width>20</width>
          <height>10</height>
          <size>
            <x>20</x>
            <y>10</y>
          </size>
          <xMin>609</xMin>
          <yMin>-88</yMin>
          <xMax>629</xMax>
          <yMax>-78</yMax>
        </rect>
        <nodeRect>
          <x>519</x>
          <y>-83</y>
          <position>
            <x>519</x>
            <y>-83</y>
          </position>
          <center>
            <x>619</x>
            <y>8</y>
          </center>
          <min>
            <x>519</x>
            <y>-83</y>
          </min>
          <max>
            <x>719</x>
            <y>99</y>
          </max>
          <width>200</width>
          <height>182</height>
          <size>
            <x>200</x>
            <y>182</y>
          </size>
          <xMin>519</xMin>
          <yMin>-83</yMin>
          <xMax>719</xMax>
          <yMax>99</yMax>
        </nodeRect>
      </inPoint>
      <outPoint type="Out">
        <id>4</id>
        <readyToInit>true</readyToInit>
        <rect>
          <x>607</x>
          <y>-146</y>
          <position>
            <x>607</x>
            <y>-146</y>
          </position>
          <center>
            <x>617</x>
            <y>-141</y>
          </center>
          <min>
            <x>607</x>
            <y>-146</y>
          </min>
          <max>
            <x>627</x>
            <y>-136</y>
          </max>
          <width>20</width>
          <height>10</height>
          <size>
            <x>20</x>
            <y>10</y>
          </size>
          <xMin>607</xMin>
          <yMin>-146</yMin>
          <xMax>627</xMax>
          <yMax>-136</yMax>
        </rect>
        <nodeRect>
          <x>517</x>
          <y>-321</y>
          <position>
            <x>517</x>
            <y>-321</y>
          </position>
          <center>
            <x>617</x>
            <y>-230</y>
          </center>
          <min>
            <x>517</x>
            <y>-321</y>
          </min>
          <max>
            <x>717</x>
            <y>-139</y>
          </max>
          <width>200</width>
          <height>182</height>
          <size>
            <x>200</x>
            <y>182</y>
          </size>
          <xMin>517</xMin>
          <yMin>-321</yMin>
          <xMax>717</xMax>
          <yMax>-139</yMax>
        </nodeRect>
      </outPoint>
    </Connection>
    <Connection>
      <readyToInit>true</readyToInit>
      <inPoint type="In">
        <id>137</id>
        <readyToInit>true</readyToInit>
        <rect>
          <x>613</x>
          <y>124</y>
          <position>
            <x>613</x>
            <y>124</y>
          </position>
          <center>
            <x>623</x>
            <y>129</y>
          </center>
          <min>
            <x>613</x>
            <y>124</y>
          </min>
          <max>
            <x>633</x>
            <y>134</y>
          </max>
          <width>20</width>
          <height>10</height>
          <size>
            <x>20</x>
            <y>10</y>
          </size>
          <xMin>613</xMin>
          <yMin>124</yMin>
          <xMax>633</xMax>
          <yMax>134</yMax>
        </rect>
        <nodeRect>
          <x>523</x>
          <y>129</y>
          <position>
            <x>523</x>
            <y>129</y>
          </position>
          <center>
            <x>623</x>
            <y>207</y>
          </center>
          <min>
            <x>523</x>
            <y>129</y>
          </min>
          <max>
            <x>723</x>
            <y>285</y>
          </max>
          <width>200</width>
          <height>156</height>
          <size>
            <x>200</x>
            <y>156</y>
          </size>
          <xMin>523</xMin>
          <yMin>129</yMin>
          <xMax>723</xMax>
          <yMax>285</yMax>
        </nodeRect>
      </inPoint>
      <outPoint type="Out">
        <id>135</id>
        <readyToInit>true</readyToInit>
        <rect>
          <x>609</x>
          <y>92</y>
          <position>
            <x>609</x>
            <y>92</y>
          </position>
          <center>
            <x>619</x>
            <y>97</y>
          </center>
          <min>
            <x>609</x>
            <y>92</y>
          </min>
          <max>
            <x>629</x>
            <y>102</y>
          </max>
          <width>20</width>
          <height>10</height>
          <size>
            <x>20</x>
            <y>10</y>
          </size>
          <xMin>609</xMin>
          <yMin>92</yMin>
          <xMax>629</xMax>
          <yMax>102</yMax>
        </rect>
        <nodeRect>
          <x>519</x>
          <y>-83</y>
          <position>
            <x>519</x>
            <y>-83</y>
          </position>
          <center>
            <x>619</x>
            <y>8</y>
          </center>
          <min>
            <x>519</x>
            <y>-83</y>
          </min>
          <max>
            <x>719</x>
            <y>99</y>
          </max>
          <width>200</width>
          <height>182</height>
          <size>
            <x>200</x>
            <y>182</y>
          </size>
          <xMin>519</xMin>
          <yMin>-83</yMin>
          <xMax>719</xMax>
          <yMax>99</yMax>
        </nodeRect>
      </outPoint>
    </Connection>
    <Connection>
      <readyToInit>true</readyToInit>
      <inPoint type="In">
        <id>136</id>
        <readyToInit>true</readyToInit>
        <rect>
          <x>614</x>
          <y>316</y>
          <position>
            <x>614</x>
            <y>316</y>
          </position>
          <center>
            <x>624</x>
            <y>321</y>
          </center>
          <min>
            <x>614</x>
            <y>316</y>
          </min>
          <max>
            <x>634</x>
            <y>326</y>
          </max>
          <width>20</width>
          <height>10</height>
          <size>
            <x>20</x>
            <y>10</y>
          </size>
          <xMin>614</xMin>
          <yMin>316</yMin>
          <xMax>634</xMax>
          <yMax>326</yMax>
        </rect>
        <nodeRect>
          <x>524</x>
          <y>321</y>
          <position>
            <x>524</x>
            <y>321</y>
          </position>
          <center>
            <x>624</x>
            <y>405.5</y>
          </center>
          <min>
            <x>524</x>
            <y>321</y>
          </min>
          <max>
            <x>724</x>
            <y>490</y>
          </max>
          <width>200</width>
          <height>169</height>
          <size>
            <x>200</x>
            <y>169</y>
          </size>
          <xMin>524</xMin>
          <yMin>321</yMin>
          <xMax>724</xMax>
          <yMax>490</yMax>
        </nodeRect>
      </inPoint>
      <outPoint type="Out">
        <id>137</id>
        <readyToInit>true</readyToInit>
        <rect>
          <x>613</x>
          <y>278</y>
          <position>
            <x>613</x>
            <y>278</y>
          </position>
          <center>
            <x>623</x>
            <y>283</y>
          </center>
          <min>
            <x>613</x>
            <y>278</y>
          </min>
          <max>
            <x>633</x>
            <y>288</y>
          </max>
          <width>20</width>
          <height>10</height>
          <size>
            <x>20</x>
            <y>10</y>
          </size>
          <xMin>613</xMin>
          <yMin>278</yMin>
          <xMax>633</xMax>
          <yMax>288</yMax>
        </rect>
        <nodeRect>
          <x>523</x>
          <y>129</y>
          <position>
            <x>523</x>
            <y>129</y>
          </position>
          <center>
            <x>623</x>
            <y>207</y>
          </center>
          <min>
            <x>523</x>
            <y>129</y>
          </min>
          <max>
            <x>723</x>
            <y>285</y>
          </max>
          <width>200</width>
          <height>156</height>
          <size>
            <x>200</x>
            <y>156</y>
          </size>
          <xMin>523</xMin>
          <yMin>129</yMin>
          <xMax>723</xMax>
          <yMax>285</yMax>
        </nodeRect>
      </outPoint>
    </Connection>
    <Connection>
      <readyToInit>true</readyToInit>
      <inPoint type="In">
        <id>138</id>
        <readyToInit>true</readyToInit>
        <rect>
          <x>619</x>
          <y>577</y>
          <position>
            <x>619</x>
            <y>577</y>
          </position>
          <center>
            <x>629</x>
            <y>582</y>
          </center>
          <min>
            <x>619</x>
            <y>577</y>
          </min>
          <max>
            <x>639</x>
            <y>587</y>
          </max>
          <width>20</width>
          <height>10</height>
          <size>
            <x>20</x>
            <y>10</y>
          </size>
          <xMin>619</xMin>
          <yMin>577</yMin>
          <xMax>639</xMax>
          <yMax>587</yMax>
        </rect>
        <nodeRect>
          <x>529</x>
          <y>582</y>
          <position>
            <x>529</x>
            <y>582</y>
          </position>
          <center>
            <x>629</x>
            <y>660</y>
          </center>
          <min>
            <x>529</x>
            <y>582</y>
          </min>
          <max>
            <x>729</x>
            <y>738</y>
          </max>
          <width>200</width>
          <height>156</height>
          <size>
            <x>200</x>
            <y>156</y>
          </size>
          <xMin>529</xMin>
          <yMin>582</yMin>
          <xMax>729</xMax>
          <yMax>738</yMax>
        </nodeRect>
      </inPoint>
      <outPoint type="Out">
        <id>136</id>
        <readyToInit>true</readyToInit>
        <rect>
          <x>614</x>
          <y>483</y>
          <position>
            <x>614</x>
            <y>483</y>
          </position>
          <center>
            <x>624</x>
            <y>488</y>
          </center>
          <min>
            <x>614</x>
            <y>483</y>
          </min>
          <max>
            <x>634</x>
            <y>493</y>
          </max>
          <width>20</width>
          <height>10</height>
          <size>
            <x>20</x>
            <y>10</y>
          </size>
          <xMin>614</xMin>
          <yMin>483</yMin>
          <xMax>634</xMax>
          <yMax>493</yMax>
        </rect>
        <nodeRect>
          <x>524</x>
          <y>321</y>
          <position>
            <x>524</x>
            <y>321</y>
          </position>
          <center>
            <x>624</x>
            <y>405.5</y>
          </center>
          <min>
            <x>524</x>
            <y>321</y>
          </min>
          <max>
            <x>724</x>
            <y>490</y>
          </max>
          <width>200</width>
          <height>169</height>
          <size>
            <x>200</x>
            <y>169</y>
          </size>
          <xMin>524</xMin>
          <yMin>321</yMin>
          <xMax>724</xMax>
          <yMax>490</yMax>
        </nodeRect>
      </outPoint>
    </Connection>
  </Connections>
</DialogueTree>